Metadata-Version: 1.1
Name: ahmetin-k-t-phanesi
Version: 12
Summary: nanayı kütüphanesi
Home-page: UNKNOWN
Author: Goretypes
Author-email: coretypes@gmail.com
License: MIT
Keywords: calculator
Platform: UNKNOWN
Classifier: Development Status :: 5 - Production/Stable
Classifier: Intended Audience :: Education
Classifier: Operating System :: Microsoft :: Windows :: Windows 10
Classifier: License :: OSI Approved :: MIT License
Classifier: Programming Language :: Python :: 3
